starmerge/__init__.py
starmerge/lib/__init__.py
starmerge/lib/class_group_utils.py
starmerge/lib/config_utils.py
starmerge/lib/create_tailwind_merge.py
starmerge/lib/default_config.py
starmerge/lib/extend_tailwind_merge.py
starmerge/lib/from_theme.py
starmerge/lib/generated_types.py
starmerge/lib/lru_cache.py
starmerge/lib/merge_classlist.py
starmerge/lib/merge_configs.py
starmerge/lib/parse_class_name.py
starmerge/lib/sort_modifiers.py
starmerge/lib/tw_join.py
starmerge/lib/tw_merge.py
starmerge/lib/types.py
starmerge/lib/validators.py
starmerge-0.2.0.dist-info/METADATA
starmerge-0.2.0.dist-info/WHEEL
starmerge-0.2.0.dist-info/licenses/LICENSE
starmerge-0.2.0.dist-info/RECORD
