Metadata-Version: 2.4
Name: starmerge
Version: 0.2.0
Summary: A comprehensive Python port of tailwind-merge - intelligently merge Tailwind CSS classes
Project-URL: Homepage, https://github.com/banditburai/starmerge
Project-URL: Documentation, https://github.com/banditburai/starmerge#readme
Project-URL: Repository, https://github.com/banditburai/starmerge
Project-URL: Bug Tracker, https://github.com/banditburai/starmerge/issues
Project-URL: Original Project, https://github.com/dcastil/tailwind-merge
Author-email: promptsiren <promptsiren@gmail.com>
License: MIT
License-File: LICENSE
Keywords: classes,css,merge,tailwind,tailwindcss,utility
Classifier: Development Status :: 4 - Beta
Classifier: Intended Audience :: Developers
Classifier: License :: OSI Approved :: MIT License
Classifier: Programming Language :: Python :: 3
Classifier: Programming Language :: Python :: 3.11
Classifier: Programming Language :: Python :: 3.12
Classifier: Programming Language :: Python :: 3.13
Classifier: Topic :: Software Development :: Libraries :: Python Modules
Classifier: Topic :: Software Development :: User Interfaces
Classifier: Topic :: Text Processing :: Markup :: HTML
Requires-Python: >=3.11
